Metadata-Version: 2.1
Name: sixl
Version: 0.1
Summary: IPython inline plots and images through Sixel.
Home-page: https://github.com/mkardas/sixl
Author: Marcin Kardas
License: MIT
Keywords: sixel ipython
Platform: UNKNOWN
Classifier: Development Status :: 3 - Alpha
Classifier: Topic :: Software Development :: Libraries
Classifier: License :: OSI Approved :: MIT License
